[
  {
    "id": "george_best_253899",
    "url": "https://www.brainyquote.com/quotes/george_best_253899",
    "topic": "Age Quotes",
    "page": "page 1"
  },
  {
    "id": "alexandra_paul_387900",
    "url": "https://www.brainyquote.com/quotes/alexandra_paul_387900",
    "topic": "Age Quotes",
    "page": "page 1"
  },
  {
    "id": "e_b_white_100103",
    "url": "https://www.brainyquote.com/quotes/e_b_white_100103",
    "topic": "Age Quotes",
    "page": "page 1"
  },
  {
    "id": "dale_earnhardt_253600",
    "url": "https://www.brainyquote.com/quotes/dale_earnhardt_253600",
    "topic": "Age Quotes",
    "page": "page 1"
  },
  {
    "id": "james_woolsey_509785",
    "url": "https://www.brainyquote.com/quotes/james_woolsey_509785",
    "topic": "Age Quotes",
    "page": "page 1"
  },
  {
    "id": "e_l_doctorow_154857",
    "url": "https://www.brainyquote.com/quotes/e_l_doctorow_154857",
    "topic": "Age Quotes",
    "page": "page 1"
  },
  {
    "id": "mario_lopez_300197",
    "url": "https://www.brainyquote.com/quotes/mario_lopez_300197",
    "topic": "Age Quotes",
    "page": "page 1"
  },
  {
    "id": "louis_c_k_452732",
    "url": "https://www.brainyquote.com/quotes/louis_c_k_452732",
    "topic": "Age Quotes",
    "page": "page 1"
  },
  {
    "id": "alfred_p_sloan_194030",
    "url": "https://www.brainyquote.com/quotes/alfred_p_sloan_194030",
    "topic": "Age Quotes",
    "page": "page 1"
  },
  {
    "id": "michael_bay_211109",
    "url": "https://www.brainyquote.com/quotes/michael_bay_211109",
    "topic": "Age Quotes",
    "page": "page 1"
  },
  {
    "id": "mitch_hedberg_297438",
    "url": "https://www.brainyquote.com/quotes/mitch_hedberg_297438",
    "topic": "Age Quotes",
    "page": "page 1"
  },
  {
    "id": "scott_baio_419202",
    "url": "https://www.brainyquote.com/quotes/scott_baio_419202",
    "topic": "Age Quotes",
    "page": "page 1"
  },
  {
    "id": "jason_behr_387816",
    "url": "https://www.brainyquote.com/quotes/jason_behr_387816",
    "topic": "Age Quotes",
    "page": "page 1"
  },
  {
    "id": "dudley_moore_195256",
    "url": "https://www.brainyquote.com/quotes/dudley_moore_195256",
    "topic": "Age Quotes",
    "page": "page 1"
  },
  {
    "id": "brock_yates_296273",
    "url": "https://www.brainyquote.com/quotes/brock_yates_296273",
    "topic": "Age Quotes",
    "page": "page 1"
  },
  {
    "id": "elon_musk_567216",
    "url": "https://www.brainyquote.com/quotes/elon_musk_567216",
    "topic": "Age Quotes",
    "page": "page 1"
  },
  {
    "id": "rita_rudner_122725",
    "url": "https://www.brainyquote.com/quotes/rita_rudner_122725",
    "topic": "Age Quotes",
    "page": "page 1"
  },
  {
    "id": "rudolf_diesel_182177",
    "url": "https://www.brainyquote.com/quotes/rudolf_diesel_182177",
    "topic": "Age Quotes",
    "page": "page 1"
  },
  {
    "id": "lara_flynn_boyle_333193",
    "url": "https://www.brainyquote.com/quotes/lara_flynn_boyle_333193",
    "topic": "Age Quotes",
    "page": "page 1"
  },
  {
    "id": "gary_oldman_415708",
    "url": "https://www.brainyquote.com/quotes/gary_oldman_415708",
    "topic": "Age Quotes",
    "page": "page 1"
  },
  {
    "id": "jordana_brewster_432723",
    "url": "https://www.brainyquote.com/quotes/jordana_brewster_432723",
    "topic": "Age Quotes",
    "page": "page 1"
  },
  {
    "id": "lawrence_summers_187383",
    "url": "https://www.brainyquote.com/quotes/lawrence_summers_187383",
    "topic": "Age Quotes",
    "page": "page 1"
  },
  {
    "id": "marshall_mcluhan_102118",
    "url": "https://www.brainyquote.com/quotes/marshall_mcluhan_102118",
    "topic": "Age Quotes",
    "page": "page 1"
  },
  {
    "id": "richard_hammond_498448",
    "url": "https://www.brainyquote.com/quotes/richard_hammond_498448",
    "topic": "Age Quotes",
    "page": "page 1"
  },
  {
    "id": "keanu_reeves_369028",
    "url": "https://www.brainyquote.com/quotes/keanu_reeves_369028",
    "topic": "Age Quotes",
    "page": "page 1"
  },
  {
    "id": "casey_james_523245",
    "url": "https://www.brainyquote.com/quotes/casey_james_523245",
    "topic": "Age Quotes",
    "page": "page 1"
  },
  {
    "id": "mario_andretti_460471",
    "url": "https://www.brainyquote.com/quotes/mario_andretti_460471",
    "topic": "Age Quotes",
    "page": "page 1"
  },
  {
    "id": "al_gore_457740",
    "url": "https://www.brainyquote.com/quotes/al_gore_457740",
    "topic": "Age Quotes",
    "page": "page 1"
  },
  {
    "id": "markpaul_gosselaar_375089",
    "url": "https://www.brainyquote.com/quotes/markpaul_gosselaar_375089",
    "topic": "Age Quotes",
    "page": "page 1"
  },
  {
    "id": "david_attenborough_214826",
    "url": "https://www.brainyquote.com/quotes/david_attenborough_214826",
    "topic": "Age Quotes",
    "page": "page 1"
  },
  {
    "id": "tpain_510714",
    "url": "https://www.brainyquote.com/quotes/tpain_510714",
    "topic": "Age Quotes",
    "page": "page 1"
  },
  {
    "id": "peta_wilson_424449",
    "url": "https://www.brainyquote.com/quotes/peta_wilson_424449",
    "topic": "Age Quotes",
    "page": "page 1"
  },
  {
    "id": "jim_demint_450035",
    "url": "https://www.brainyquote.com/quotes/jim_demint_450035",
    "topic": "Age Quotes",
    "page": "page 1"
  },
  {
    "id": "bill_gates_389269",
    "url": "https://www.brainyquote.com/quotes/bill_gates_389269",
    "topic": "Age Quotes",
    "page": "page 1"
  },
  {
    "id": "lady_gaga_600189",
    "url": "https://www.brainyquote.com/quotes/lady_gaga_600189",
    "topic": "Age Quotes",
    "page": "page 1"
  },
  {
    "id": "jeff_foxworthy_183456",
    "url": "https://www.brainyquote.com/quotes/jeff_foxworthy_183456",
    "topic": "Age Quotes",
    "page": "page 1"
  },
  {
    "id": "elon_musk_567300",
    "url": "https://www.brainyquote.com/quotes/elon_musk_567300",
    "topic": "Age Quotes",
    "page": "page 1"
  },
  {
    "id": "gore_vidal_112493",
    "url": "https://www.brainyquote.com/quotes/gore_vidal_112493",
    "topic": "Age Quotes",
    "page": "page 1"
  },
  {
    "id": "lee_iacocca_456996",
    "url": "https://www.brainyquote.com/quotes/lee_iacocca_456996",
    "topic": "Age Quotes",
    "page": "page 1"
  },
  {
    "id": "tom_arnold_405053",
    "url": "https://www.brainyquote.com/quotes/tom_arnold_405053",
    "topic": "Age Quotes",
    "page": "page 1"
  },
  {
    "id": "ludacris_424222",
    "url": "https://www.brainyquote.com/quotes/ludacris_424222",
    "topic": "Age Quotes",
    "page": "page 1"
  },
  {
    "id": "ryan_tedder_497586",
    "url": "https://www.brainyquote.com/quotes/ryan_tedder_497586",
    "topic": "Age Quotes",
    "page": "page 1"
  },
  {
    "id": "matthew_barney_221011",
    "url": "https://www.brainyquote.com/quotes/matthew_barney_221011",
    "topic": "Age Quotes",
    "page": "page 1"
  },
  {
    "id": "elon_musk_567232",
    "url": "https://www.brainyquote.com/quotes/elon_musk_567232",
    "topic": "Age Quotes",
    "page": "page 1"
  },
  {
    "id": "robert_herjavec_521248",
    "url": "https://www.brainyquote.com/quotes/robert_herjavec_521248",
    "topic": "Age Quotes",
    "page": "page 1"
  },
  {
    "id": "gordon_sinclair_292230",
    "url": "https://www.brainyquote.com/quotes/gordon_sinclair_292230",
    "topic": "Age Quotes",
    "page": "page 1"
  },
  {
    "id": "russell_baker_146118",
    "url": "https://www.brainyquote.com/quotes/russell_baker_146118",
    "topic": "Age Quotes",
    "page": "page 1"
  },
  {
    "id": "sammy_davis_jr_334351",
    "url": "https://www.brainyquote.com/quotes/sammy_davis_jr_334351",
    "topic": "Age Quotes",
    "page": "page 1"
  },
  {
    "id": "ariel_gore_527268",
    "url": "https://www.brainyquote.com/quotes/ariel_gore_527268",
    "topic": "Age Quotes",
    "page": "page 1"
  },
  {
    "id": "e_joseph_cossman_176361",
    "url": "https://www.brainyquote.com/quotes/e_joseph_cossman_176361",
    "topic": "Age Quotes",
    "page": "page 1"
  },
  {
    "id": "a_j_foyt_226701",
    "url": "https://www.brainyquote.com/quotes/a_j_foyt_226701",
    "topic": "Age Quotes",
    "page": "page 1"
  },
  {
    "id": "bud_abbott_208475",
    "url": "https://www.brainyquote.com/quotes/bud_abbott_208475",
    "topic": "Age Quotes",
    "page": "page 1"
  },
  {
    "id": "dave_barry_102319",
    "url": "https://www.brainyquote.com/quotes/dave_barry_102319",
    "topic": "Age Quotes",
    "page": "page 1"
  },
  {
    "id": "catherine_bell_298774",
    "url": "https://www.brainyquote.com/quotes/catherine_bell_298774",
    "topic": "Age Quotes",
    "page": "page 1"
  },
  {
    "id": "james_cagney_179645",
    "url": "https://www.brainyquote.com/quotes/james_cagney_179645",
    "topic": "Age Quotes",
    "page": "page 1"
  },
  {
    "id": "marc_andreessen_419426",
    "url": "https://www.brainyquote.com/quotes/marc_andreessen_419426",
    "topic": "Age Quotes",
    "page": "page 1"
  },
  {
    "id": "carroll_shelby_427620",
    "url": "https://www.brainyquote.com/quotes/carroll_shelby_427620",
    "topic": "Age Quotes",
    "page": "page 1"
  },
  {
    "id": "robbie_coltrane_214647",
    "url": "https://www.brainyquote.com/quotes/robbie_coltrane_214647",
    "topic": "Age Quotes",
    "page": "page 1"
  },
  {
    "id": "evel_knievel_326222",
    "url": "https://www.brainyquote.com/quotes/evel_knievel_326222",
    "topic": "Age Quotes",
    "page": "page 1"
  },
  {
    "id": "paul_fussell_402033",
    "url": "https://www.brainyquote.com/quotes/paul_fussell_402033",
    "topic": "Age Quotes",
    "page": "page 1"
  },
  {
    "id": "george_best_253899",
    "url": "https://www.brainyquote.com/quotes/george_best_253899",
    "topic": "Age Quotes",
    "page": "page 2"
  },
  {
    "id": "alexandra_paul_387900",
    "url": "https://www.brainyquote.com/quotes/alexandra_paul_387900",
    "topic": "Age Quotes",
    "page": "page 2"
  },
  {
    "id": "e_b_white_100103",
    "url": "https://www.brainyquote.com/quotes/e_b_white_100103",
    "topic": "Age Quotes",
    "page": "page 2"
  },
  {
    "id": "dale_earnhardt_253600",
    "url": "https://www.brainyquote.com/quotes/dale_earnhardt_253600",
    "topic": "Age Quotes",
    "page": "page 2"
  },
  {
    "id": "james_woolsey_509785",
    "url": "https://www.brainyquote.com/quotes/james_woolsey_509785",
    "topic": "Age Quotes",
    "page": "page 2"
  },
  {
    "id": "e_l_doctorow_154857",
    "url": "https://www.brainyquote.com/quotes/e_l_doctorow_154857",
    "topic": "Age Quotes",
    "page": "page 2"
  },
  {
    "id": "mario_lopez_300197",
    "url": "https://www.brainyquote.com/quotes/mario_lopez_300197",
    "topic": "Age Quotes",
    "page": "page 2"
  },
  {
    "id": "louis_c_k_452732",
    "url": "https://www.brainyquote.com/quotes/louis_c_k_452732",
    "topic": "Age Quotes",
    "page": "page 2"
  },
  {
    "id": "alfred_p_sloan_194030",
    "url": "https://www.brainyquote.com/quotes/alfred_p_sloan_194030",
    "topic": "Age Quotes",
    "page": "page 2"
  },
  {
    "id": "michael_bay_211109",
    "url": "https://www.brainyquote.com/quotes/michael_bay_211109",
    "topic": "Age Quotes",
    "page": "page 2"
  },
  {
    "id": "mitch_hedberg_297438",
    "url": "https://www.brainyquote.com/quotes/mitch_hedberg_297438",
    "topic": "Age Quotes",
    "page": "page 2"
  },
  {
    "id": "scott_baio_419202",
    "url": "https://www.brainyquote.com/quotes/scott_baio_419202",
    "topic": "Age Quotes",
    "page": "page 2"
  },
  {
    "id": "jason_behr_387816",
    "url": "https://www.brainyquote.com/quotes/jason_behr_387816",
    "topic": "Age Quotes",
    "page": "page 2"
  },
  {
    "id": "dudley_moore_195256",
    "url": "https://www.brainyquote.com/quotes/dudley_moore_195256",
    "topic": "Age Quotes",
    "page": "page 2"
  },
  {
    "id": "brock_yates_296273",
    "url": "https://www.brainyquote.com/quotes/brock_yates_296273",
    "topic": "Age Quotes",
    "page": "page 2"
  },
  {
    "id": "elon_musk_567216",
    "url": "https://www.brainyquote.com/quotes/elon_musk_567216",
    "topic": "Age Quotes",
    "page": "page 2"
  },
  {
    "id": "rita_rudner_122725",
    "url": "https://www.brainyquote.com/quotes/rita_rudner_122725",
    "topic": "Age Quotes",
    "page": "page 2"
  },
  {
    "id": "rudolf_diesel_182177",
    "url": "https://www.brainyquote.com/quotes/rudolf_diesel_182177",
    "topic": "Age Quotes",
    "page": "page 2"
  },
  {
    "id": "lara_flynn_boyle_333193",
    "url": "https://www.brainyquote.com/quotes/lara_flynn_boyle_333193",
    "topic": "Age Quotes",
    "page": "page 2"
  },
  {
    "id": "gary_oldman_415708",
    "url": "https://www.brainyquote.com/quotes/gary_oldman_415708",
    "topic": "Age Quotes",
    "page": "page 2"
  },
  {
    "id": "jordana_brewster_432723",
    "url": "https://www.brainyquote.com/quotes/jordana_brewster_432723",
    "topic": "Age Quotes",
    "page": "page 2"
  },
  {
    "id": "lawrence_summers_187383",
    "url": "https://www.brainyquote.com/quotes/lawrence_summers_187383",
    "topic": "Age Quotes",
    "page": "page 2"
  },
  {
    "id": "marshall_mcluhan_102118",
    "url": "https://www.brainyquote.com/quotes/marshall_mcluhan_102118",
    "topic": "Age Quotes",
    "page": "page 2"
  },
  {
    "id": "richard_hammond_498448",
    "url": "https://www.brainyquote.com/quotes/richard_hammond_498448",
    "topic": "Age Quotes",
    "page": "page 2"
  },
  {
    "id": "keanu_reeves_369028",
    "url": "https://www.brainyquote.com/quotes/keanu_reeves_369028",
    "topic": "Age Quotes",
    "page": "page 2"
  },
  {
    "id": "casey_james_523245",
    "url": "https://www.brainyquote.com/quotes/casey_james_523245",
    "topic": "Age Quotes",
    "page": "page 2"
  },
  {
    "id": "mario_andretti_460471",
    "url": "https://www.brainyquote.com/quotes/mario_andretti_460471",
    "topic": "Age Quotes",
    "page": "page 2"
  },
  {
    "id": "al_gore_457740",
    "url": "https://www.brainyquote.com/quotes/al_gore_457740",
    "topic": "Age Quotes",
    "page": "page 2"
  },
  {
    "id": "markpaul_gosselaar_375089",
    "url": "https://www.brainyquote.com/quotes/markpaul_gosselaar_375089",
    "topic": "Age Quotes",
    "page": "page 2"
  },
  {
    "id": "david_attenborough_214826",
    "url": "https://www.brainyquote.com/quotes/david_attenborough_214826",
    "topic": "Age Quotes",
    "page": "page 2"
  },
  {
    "id": "tpain_510714",
    "url": "https://www.brainyquote.com/quotes/tpain_510714",
    "topic": "Age Quotes",
    "page": "page 2"
  },
  {
    "id": "peta_wilson_424449",
    "url": "https://www.brainyquote.com/quotes/peta_wilson_424449",
    "topic": "Age Quotes",
    "page": "page 2"
  },
  {
    "id": "jim_demint_450035",
    "url": "https://www.brainyquote.com/quotes/jim_demint_450035",
    "topic": "Age Quotes",
    "page": "page 2"
  },
  {
    "id": "bill_gates_389269",
    "url": "https://www.brainyquote.com/quotes/bill_gates_389269",
    "topic": "Age Quotes",
    "page": "page 2"
  },
  {
    "id": "lady_gaga_600189",
    "url": "https://www.brainyquote.com/quotes/lady_gaga_600189",
    "topic": "Age Quotes",
    "page": "page 2"
  },
  {
    "id": "jeff_foxworthy_183456",
    "url": "https://www.brainyquote.com/quotes/jeff_foxworthy_183456",
    "topic": "Age Quotes",
    "page": "page 2"
  },
  {
    "id": "elon_musk_567300",
    "url": "https://www.brainyquote.com/quotes/elon_musk_567300",
    "topic": "Age Quotes",
    "page": "page 2"
  },
  {
    "id": "gore_vidal_112493",
    "url": "https://www.brainyquote.com/quotes/gore_vidal_112493",
    "topic": "Age Quotes",
    "page": "page 2"
  },
  {
    "id": "lee_iacocca_456996",
    "url": "https://www.brainyquote.com/quotes/lee_iacocca_456996",
    "topic": "Age Quotes",
    "page": "page 2"
  },
  {
    "id": "tom_arnold_405053",
    "url": "https://www.brainyquote.com/quotes/tom_arnold_405053",
    "topic": "Age Quotes",
    "page": "page 2"
  },
  {
    "id": "ludacris_424222",
    "url": "https://www.brainyquote.com/quotes/ludacris_424222",
    "topic": "Age Quotes",
    "page": "page 2"
  },
  {
    "id": "ryan_tedder_497586",
    "url": "https://www.brainyquote.com/quotes/ryan_tedder_497586",
    "topic": "Age Quotes",
    "page": "page 2"
  },
  {
    "id": "matthew_barney_221011",
    "url": "https://www.brainyquote.com/quotes/matthew_barney_221011",
    "topic": "Age Quotes",
    "page": "page 2"
  },
  {
    "id": "elon_musk_567232",
    "url": "https://www.brainyquote.com/quotes/elon_musk_567232",
    "topic": "Age Quotes",
    "page": "page 2"
  },
  {
    "id": "robert_herjavec_521248",
    "url": "https://www.brainyquote.com/quotes/robert_herjavec_521248",
    "topic": "Age Quotes",
    "page": "page 2"
  },
  {
    "id": "gordon_sinclair_292230",
    "url": "https://www.brainyquote.com/quotes/gordon_sinclair_292230",
    "topic": "Age Quotes",
    "page": "page 2"
  },
  {
    "id": "russell_baker_146118",
    "url": "https://www.brainyquote.com/quotes/russell_baker_146118",
    "topic": "Age Quotes",
    "page": "page 2"
  },
  {
    "id": "sammy_davis_jr_334351",
    "url": "https://www.brainyquote.com/quotes/sammy_davis_jr_334351",
    "topic": "Age Quotes",
    "page": "page 2"
  },
  {
    "id": "ariel_gore_527268",
    "url": "https://www.brainyquote.com/quotes/ariel_gore_527268",
    "topic": "Age Quotes",
    "page": "page 2"
  },
  {
    "id": "e_joseph_cossman_176361",
    "url": "https://www.brainyquote.com/quotes/e_joseph_cossman_176361",
    "topic": "Age Quotes",
    "page": "page 2"
  },
  {
    "id": "a_j_foyt_226701",
    "url": "https://www.brainyquote.com/quotes/a_j_foyt_226701",
    "topic": "Age Quotes",
    "page": "page 2"
  },
  {
    "id": "bud_abbott_208475",
    "url": "https://www.brainyquote.com/quotes/bud_abbott_208475",
    "topic": "Age Quotes",
    "page": "page 2"
  },
  {
    "id": "dave_barry_102319",
    "url": "https://www.brainyquote.com/quotes/dave_barry_102319",
    "topic": "Age Quotes",
    "page": "page 2"
  },
  {
    "id": "catherine_bell_298774",
    "url": "https://www.brainyquote.com/quotes/catherine_bell_298774",
    "topic": "Age Quotes",
    "page": "page 2"
  },
  {
    "id": "james_cagney_179645",
    "url": "https://www.brainyquote.com/quotes/james_cagney_179645",
    "topic": "Age Quotes",
    "page": "page 2"
  },
  {
    "id": "marc_andreessen_419426",
    "url": "https://www.brainyquote.com/quotes/marc_andreessen_419426",
    "topic": "Age Quotes",
    "page": "page 2"
  },
  {
    "id": "carroll_shelby_427620",
    "url": "https://www.brainyquote.com/quotes/carroll_shelby_427620",
    "topic": "Age Quotes",
    "page": "page 2"
  },
  {
    "id": "robbie_coltrane_214647",
    "url": "https://www.brainyquote.com/quotes/robbie_coltrane_214647",
    "topic": "Age Quotes",
    "page": "page 2"
  },
  {
    "id": "evel_knievel_326222",
    "url": "https://www.brainyquote.com/quotes/evel_knievel_326222",
    "topic": "Age Quotes",
    "page": "page 2"
  },
  {
    "id": "paul_fussell_402033",
    "url": "https://www.brainyquote.com/quotes/paul_fussell_402033",
    "topic": "Age Quotes",
    "page": "page 2"
  },
  {
    "id": "george_best_253899",
    "url": "https://www.brainyquote.com/quotes/george_best_253899",
    "topic": "Age Quotes",
    "page": "page 3"
  },
  {
    "id": "alexandra_paul_387900",
    "url": "https://www.brainyquote.com/quotes/alexandra_paul_387900",
    "topic": "Age Quotes",
    "page": "page 3"
  },
  {
    "id": "e_b_white_100103",
    "url": "https://www.brainyquote.com/quotes/e_b_white_100103",
    "topic": "Age Quotes",
    "page": "page 3"
  },
  {
    "id": "dale_earnhardt_253600",
    "url": "https://www.brainyquote.com/quotes/dale_earnhardt_253600",
    "topic": "Age Quotes",
    "page": "page 3"
  },
  {
    "id": "james_woolsey_509785",
    "url": "https://www.brainyquote.com/quotes/james_woolsey_509785",
    "topic": "Age Quotes",
    "page": "page 3"
  },
  {
    "id": "e_l_doctorow_154857",
    "url": "https://www.brainyquote.com/quotes/e_l_doctorow_154857",
    "topic": "Age Quotes",
    "page": "page 3"
  },
  {
    "id": "mario_lopez_300197",
    "url": "https://www.brainyquote.com/quotes/mario_lopez_300197",
    "topic": "Age Quotes",
    "page": "page 3"
  },
  {
    "id": "louis_c_k_452732",
    "url": "https://www.brainyquote.com/quotes/louis_c_k_452732",
    "topic": "Age Quotes",
    "page": "page 3"
  },
  {
    "id": "alfred_p_sloan_194030",
    "url": "https://www.brainyquote.com/quotes/alfred_p_sloan_194030",
    "topic": "Age Quotes",
    "page": "page 3"
  },
  {
    "id": "michael_bay_211109",
    "url": "https://www.brainyquote.com/quotes/michael_bay_211109",
    "topic": "Age Quotes",
    "page": "page 3"
  },
  {
    "id": "mitch_hedberg_297438",
    "url": "https://www.brainyquote.com/quotes/mitch_hedberg_297438",
    "topic": "Age Quotes",
    "page": "page 3"
  },
  {
    "id": "scott_baio_419202",
    "url": "https://www.brainyquote.com/quotes/scott_baio_419202",
    "topic": "Age Quotes",
    "page": "page 3"
  },
  {
    "id": "jason_behr_387816",
    "url": "https://www.brainyquote.com/quotes/jason_behr_387816",
    "topic": "Age Quotes",
    "page": "page 3"
  },
  {
    "id": "dudley_moore_195256",
    "url": "https://www.brainyquote.com/quotes/dudley_moore_195256",
    "topic": "Age Quotes",
    "page": "page 3"
  },
  {
    "id": "brock_yates_296273",
    "url": "https://www.brainyquote.com/quotes/brock_yates_296273",
    "topic": "Age Quotes",
    "page": "page 3"
  },
  {
    "id": "elon_musk_567216",
    "url": "https://www.brainyquote.com/quotes/elon_musk_567216",
    "topic": "Age Quotes",
    "page": "page 3"
  },
  {
    "id": "rita_rudner_122725",
    "url": "https://www.brainyquote.com/quotes/rita_rudner_122725",
    "topic": "Age Quotes",
    "page": "page 3"
  },
  {
    "id": "rudolf_diesel_182177",
    "url": "https://www.brainyquote.com/quotes/rudolf_diesel_182177",
    "topic": "Age Quotes",
    "page": "page 3"
  },
  {
    "id": "lara_flynn_boyle_333193",
    "url": "https://www.brainyquote.com/quotes/lara_flynn_boyle_333193",
    "topic": "Age Quotes",
    "page": "page 3"
  },
  {
    "id": "gary_oldman_415708",
    "url": "https://www.brainyquote.com/quotes/gary_oldman_415708",
    "topic": "Age Quotes",
    "page": "page 3"
  },
  {
    "id": "jordana_brewster_432723",
    "url": "https://www.brainyquote.com/quotes/jordana_brewster_432723",
    "topic": "Age Quotes",
    "page": "page 3"
  },
  {
    "id": "lawrence_summers_187383",
    "url": "https://www.brainyquote.com/quotes/lawrence_summers_187383",
    "topic": "Age Quotes",
    "page": "page 3"
  },
  {
    "id": "marshall_mcluhan_102118",
    "url": "https://www.brainyquote.com/quotes/marshall_mcluhan_102118",
    "topic": "Age Quotes",
    "page": "page 3"
  },
  {
    "id": "richard_hammond_498448",
    "url": "https://www.brainyquote.com/quotes/richard_hammond_498448",
    "topic": "Age Quotes",
    "page": "page 3"
  },
  {
    "id": "keanu_reeves_369028",
    "url": "https://www.brainyquote.com/quotes/keanu_reeves_369028",
    "topic": "Age Quotes",
    "page": "page 3"
  },
  {
    "id": "casey_james_523245",
    "url": "https://www.brainyquote.com/quotes/casey_james_523245",
    "topic": "Age Quotes",
    "page": "page 3"
  },
  {
    "id": "mario_andretti_460471",
    "url": "https://www.brainyquote.com/quotes/mario_andretti_460471",
    "topic": "Age Quotes",
    "page": "page 3"
  },
  {
    "id": "al_gore_457740",
    "url": "https://www.brainyquote.com/quotes/al_gore_457740",
    "topic": "Age Quotes",
    "page": "page 3"
  },
  {
    "id": "markpaul_gosselaar_375089",
    "url": "https://www.brainyquote.com/quotes/markpaul_gosselaar_375089",
    "topic": "Age Quotes",
    "page": "page 3"
  },
  {
    "id": "david_attenborough_214826",
    "url": "https://www.brainyquote.com/quotes/david_attenborough_214826",
    "topic": "Age Quotes",
    "page": "page 3"
  },
  {
    "id": "tpain_510714",
    "url": "https://www.brainyquote.com/quotes/tpain_510714",
    "topic": "Age Quotes",
    "page": "page 3"
  },
  {
    "id": "peta_wilson_424449",
    "url": "https://www.brainyquote.com/quotes/peta_wilson_424449",
    "topic": "Age Quotes",
    "page": "page 3"
  },
  {
    "id": "jim_demint_450035",
    "url": "https://www.brainyquote.com/quotes/jim_demint_450035",
    "topic": "Age Quotes",
    "page": "page 3"
  },
  {
    "id": "bill_gates_389269",
    "url": "https://www.brainyquote.com/quotes/bill_gates_389269",
    "topic": "Age Quotes",
    "page": "page 3"
  },
  {
    "id": "lady_gaga_600189",
    "url": "https://www.brainyquote.com/quotes/lady_gaga_600189",
    "topic": "Age Quotes",
    "page": "page 3"
  },
  {
    "id": "jeff_foxworthy_183456",
    "url": "https://www.brainyquote.com/quotes/jeff_foxworthy_183456",
    "topic": "Age Quotes",
    "page": "page 3"
  },
  {
    "id": "elon_musk_567300",
    "url": "https://www.brainyquote.com/quotes/elon_musk_567300",
    "topic": "Age Quotes",
    "page": "page 3"
  },
  {
    "id": "gore_vidal_112493",
    "url": "https://www.brainyquote.com/quotes/gore_vidal_112493",
    "topic": "Age Quotes",
    "page": "page 3"
  },
  {
    "id": "lee_iacocca_456996",
    "url": "https://www.brainyquote.com/quotes/lee_iacocca_456996",
    "topic": "Age Quotes",
    "page": "page 3"
  },
  {
    "id": "tom_arnold_405053",
    "url": "https://www.brainyquote.com/quotes/tom_arnold_405053",
    "topic": "Age Quotes",
    "page": "page 3"
  },
  {
    "id": "ludacris_424222",
    "url": "https://www.brainyquote.com/quotes/ludacris_424222",
    "topic": "Age Quotes",
    "page": "page 3"
  },
  {
    "id": "ryan_tedder_497586",
    "url": "https://www.brainyquote.com/quotes/ryan_tedder_497586",
    "topic": "Age Quotes",
    "page": "page 3"
  },
  {
    "id": "matthew_barney_221011",
    "url": "https://www.brainyquote.com/quotes/matthew_barney_221011",
    "topic": "Age Quotes",
    "page": "page 3"
  },
  {
    "id": "elon_musk_567232",
    "url": "https://www.brainyquote.com/quotes/elon_musk_567232",
    "topic": "Age Quotes",
    "page": "page 3"
  },
  {
    "id": "robert_herjavec_521248",
    "url": "https://www.brainyquote.com/quotes/robert_herjavec_521248",
    "topic": "Age Quotes",
    "page": "page 3"
  },
  {
    "id": "gordon_sinclair_292230",
    "url": "https://www.brainyquote.com/quotes/gordon_sinclair_292230",
    "topic": "Age Quotes",
    "page": "page 3"
  },
  {
    "id": "russell_baker_146118",
    "url": "https://www.brainyquote.com/quotes/russell_baker_146118",
    "topic": "Age Quotes",
    "page": "page 3"
  },
  {
    "id": "sammy_davis_jr_334351",
    "url": "https://www.brainyquote.com/quotes/sammy_davis_jr_334351",
    "topic": "Age Quotes",
    "page": "page 3"
  },
  {
    "id": "ariel_gore_527268",
    "url": "https://www.brainyquote.com/quotes/ariel_gore_527268",
    "topic": "Age Quotes",
    "page": "page 3"
  },
  {
    "id": "e_joseph_cossman_176361",
    "url": "https://www.brainyquote.com/quotes/e_joseph_cossman_176361",
    "topic": "Age Quotes",
    "page": "page 3"
  },
  {
    "id": "a_j_foyt_226701",
    "url": "https://www.brainyquote.com/quotes/a_j_foyt_226701",
    "topic": "Age Quotes",
    "page": "page 3"
  },
  {
    "id": "bud_abbott_208475",
    "url": "https://www.brainyquote.com/quotes/bud_abbott_208475",
    "topic": "Age Quotes",
    "page": "page 3"
  },
  {
    "id": "dave_barry_102319",
    "url": "https://www.brainyquote.com/quotes/dave_barry_102319",
    "topic": "Age Quotes",
    "page": "page 3"
  },
  {
    "id": "catherine_bell_298774",
    "url": "https://www.brainyquote.com/quotes/catherine_bell_298774",
    "topic": "Age Quotes",
    "page": "page 3"
  },
  {
    "id": "james_cagney_179645",
    "url": "https://www.brainyquote.com/quotes/james_cagney_179645",
    "topic": "Age Quotes",
    "page": "page 3"
  },
  {
    "id": "marc_andreessen_419426",
    "url": "https://www.brainyquote.com/quotes/marc_andreessen_419426",
    "topic": "Age Quotes",
    "page": "page 3"
  },
  {
    "id": "carroll_shelby_427620",
    "url": "https://www.brainyquote.com/quotes/carroll_shelby_427620",
    "topic": "Age Quotes",
    "page": "page 3"
  },
  {
    "id": "robbie_coltrane_214647",
    "url": "https://www.brainyquote.com/quotes/robbie_coltrane_214647",
    "topic": "Age Quotes",
    "page": "page 3"
  },
  {
    "id": "evel_knievel_326222",
    "url": "https://www.brainyquote.com/quotes/evel_knievel_326222",
    "topic": "Age Quotes",
    "page": "page 3"
  },
  {
    "id": "paul_fussell_402033",
    "url": "https://www.brainyquote.com/quotes/paul_fussell_402033",
    "topic": "Age Quotes",
    "page": "page 3"
  },
  {
    "id": "george_best_253899",
    "url": "https://www.brainyquote.com/quotes/george_best_253899",
    "topic": "Age Quotes",
    "page": "page 4"
  },
  {
    "id": "alexandra_paul_387900",
    "url": "https://www.brainyquote.com/quotes/alexandra_paul_387900",
    "topic": "Age Quotes",
    "page": "page 4"
  },
  {
    "id": "e_b_white_100103",
    "url": "https://www.brainyquote.com/quotes/e_b_white_100103",
    "topic": "Age Quotes",
    "page": "page 4"
  },
  {
    "id": "dale_earnhardt_253600",
    "url": "https://www.brainyquote.com/quotes/dale_earnhardt_253600",
    "topic": "Age Quotes",
    "page": "page 4"
  },
  {
    "id": "james_woolsey_509785",
    "url": "https://www.brainyquote.com/quotes/james_woolsey_509785",
    "topic": "Age Quotes",
    "page": "page 4"
  },
  {
    "id": "e_l_doctorow_154857",
    "url": "https://www.brainyquote.com/quotes/e_l_doctorow_154857",
    "topic": "Age Quotes",
    "page": "page 4"
  },
  {
    "id": "mario_lopez_300197",
    "url": "https://www.brainyquote.com/quotes/mario_lopez_300197",
    "topic": "Age Quotes",
    "page": "page 4"
  },
  {
    "id": "louis_c_k_452732",
    "url": "https://www.brainyquote.com/quotes/louis_c_k_452732",
    "topic": "Age Quotes",
    "page": "page 4"
  },
  {
    "id": "alfred_p_sloan_194030",
    "url": "https://www.brainyquote.com/quotes/alfred_p_sloan_194030",
    "topic": "Age Quotes",
    "page": "page 4"
  },
  {
    "id": "michael_bay_211109",
    "url": "https://www.brainyquote.com/quotes/michael_bay_211109",
    "topic": "Age Quotes",
    "page": "page 4"
  },
  {
    "id": "mitch_hedberg_297438",
    "url": "https://www.brainyquote.com/quotes/mitch_hedberg_297438",
    "topic": "Age Quotes",
    "page": "page 4"
  },
  {
    "id": "scott_baio_419202",
    "url": "https://www.brainyquote.com/quotes/scott_baio_419202",
    "topic": "Age Quotes",
    "page": "page 4"
  },
  {
    "id": "jason_behr_387816",
    "url": "https://www.brainyquote.com/quotes/jason_behr_387816",
    "topic": "Age Quotes",
    "page": "page 4"
  },
  {
    "id": "dudley_moore_195256",
    "url": "https://www.brainyquote.com/quotes/dudley_moore_195256",
    "topic": "Age Quotes",
    "page": "page 4"
  },
  {
    "id": "brock_yates_296273",
    "url": "https://www.brainyquote.com/quotes/brock_yates_296273",
    "topic": "Age Quotes",
    "page": "page 4"
  },
  {
    "id": "elon_musk_567216",
    "url": "https://www.brainyquote.com/quotes/elon_musk_567216",
    "topic": "Age Quotes",
    "page": "page 4"
  },
  {
    "id": "rita_rudner_122725",
    "url": "https://www.brainyquote.com/quotes/rita_rudner_122725",
    "topic": "Age Quotes",
    "page": "page 4"
  },
  {
    "id": "rudolf_diesel_182177",
    "url": "https://www.brainyquote.com/quotes/rudolf_diesel_182177",
    "topic": "Age Quotes",
    "page": "page 4"
  },
  {
    "id": "lara_flynn_boyle_333193",
    "url": "https://www.brainyquote.com/quotes/lara_flynn_boyle_333193",
    "topic": "Age Quotes",
    "page": "page 4"
  },
  {
    "id": "gary_oldman_415708",
    "url": "https://www.brainyquote.com/quotes/gary_oldman_415708",
    "topic": "Age Quotes",
    "page": "page 4"
  },
  {
    "id": "jordana_brewster_432723",
    "url": "https://www.brainyquote.com/quotes/jordana_brewster_432723",
    "topic": "Age Quotes",
    "page": "page 4"
  },
  {
    "id": "lawrence_summers_187383",
    "url": "https://www.brainyquote.com/quotes/lawrence_summers_187383",
    "topic": "Age Quotes",
    "page": "page 4"
  },
  {
    "id": "marshall_mcluhan_102118",
    "url": "https://www.brainyquote.com/quotes/marshall_mcluhan_102118",
    "topic": "Age Quotes",
    "page": "page 4"
  },
  {
    "id": "richard_hammond_498448",
    "url": "https://www.brainyquote.com/quotes/richard_hammond_498448",
    "topic": "Age Quotes",
    "page": "page 4"
  },
  {
    "id": "keanu_reeves_369028",
    "url": "https://www.brainyquote.com/quotes/keanu_reeves_369028",
    "topic": "Age Quotes",
    "page": "page 4"
  },
  {
    "id": "casey_james_523245",
    "url": "https://www.brainyquote.com/quotes/casey_james_523245",
    "topic": "Age Quotes",
    "page": "page 4"
  },
  {
    "id": "mario_andretti_460471",
    "url": "https://www.brainyquote.com/quotes/mario_andretti_460471",
    "topic": "Age Quotes",
    "page": "page 4"
  },
  {
    "id": "al_gore_457740",
    "url": "https://www.brainyquote.com/quotes/al_gore_457740",
    "topic": "Age Quotes",
    "page": "page 4"
  },
  {
    "id": "markpaul_gosselaar_375089",
    "url": "https://www.brainyquote.com/quotes/markpaul_gosselaar_375089",
    "topic": "Age Quotes",
    "page": "page 4"
  },
  {
    "id": "david_attenborough_214826",
    "url": "https://www.brainyquote.com/quotes/david_attenborough_214826",
    "topic": "Age Quotes",
    "page": "page 4"
  },
  {
    "id": "tpain_510714",
    "url": "https://www.brainyquote.com/quotes/tpain_510714",
    "topic": "Age Quotes",
    "page": "page 4"
  },
  {
    "id": "peta_wilson_424449",
    "url": "https://www.brainyquote.com/quotes/peta_wilson_424449",
    "topic": "Age Quotes",
    "page": "page 4"
  },
  {
    "id": "jim_demint_450035",
    "url": "https://www.brainyquote.com/quotes/jim_demint_450035",
    "topic": "Age Quotes",
    "page": "page 4"
  },
  {
    "id": "bill_gates_389269",
    "url": "https://www.brainyquote.com/quotes/bill_gates_389269",
    "topic": "Age Quotes",
    "page": "page 4"
  },
  {
    "id": "lady_gaga_600189",
    "url": "https://www.brainyquote.com/quotes/lady_gaga_600189",
    "topic": "Age Quotes",
    "page": "page 4"
  },
  {
    "id": "jeff_foxworthy_183456",
    "url": "https://www.brainyquote.com/quotes/jeff_foxworthy_183456",
    "topic": "Age Quotes",
    "page": "page 4"
  },
  {
    "id": "elon_musk_567300",
    "url": "https://www.brainyquote.com/quotes/elon_musk_567300",
    "topic": "Age Quotes",
    "page": "page 4"
  },
  {
    "id": "gore_vidal_112493",
    "url": "https://www.brainyquote.com/quotes/gore_vidal_112493",
    "topic": "Age Quotes",
    "page": "page 4"
  },
  {
    "id": "lee_iacocca_456996",
    "url": "https://www.brainyquote.com/quotes/lee_iacocca_456996",
    "topic": "Age Quotes",
    "page": "page 4"
  },
  {
    "id": "tom_arnold_405053",
    "url": "https://www.brainyquote.com/quotes/tom_arnold_405053",
    "topic": "Age Quotes",
    "page": "page 4"
  },
  {
    "id": "ludacris_424222",
    "url": "https://www.brainyquote.com/quotes/ludacris_424222",
    "topic": "Age Quotes",
    "page": "page 4"
  },
  {
    "id": "ryan_tedder_497586",
    "url": "https://www.brainyquote.com/quotes/ryan_tedder_497586",
    "topic": "Age Quotes",
    "page": "page 4"
  },
  {
    "id": "matthew_barney_221011",
    "url": "https://www.brainyquote.com/quotes/matthew_barney_221011",
    "topic": "Age Quotes",
    "page": "page 4"
  },
  {
    "id": "elon_musk_567232",
    "url": "https://www.brainyquote.com/quotes/elon_musk_567232",
    "topic": "Age Quotes",
    "page": "page 4"
  },
  {
    "id": "robert_herjavec_521248",
    "url": "https://www.brainyquote.com/quotes/robert_herjavec_521248",
    "topic": "Age Quotes",
    "page": "page 4"
  },
  {
    "id": "gordon_sinclair_292230",
    "url": "https://www.brainyquote.com/quotes/gordon_sinclair_292230",
    "topic": "Age Quotes",
    "page": "page 4"
  },
  {
    "id": "russell_baker_146118",
    "url": "https://www.brainyquote.com/quotes/russell_baker_146118",
    "topic": "Age Quotes",
    "page": "page 4"
  },
  {
    "id": "sammy_davis_jr_334351",
    "url": "https://www.brainyquote.com/quotes/sammy_davis_jr_334351",
    "topic": "Age Quotes",
    "page": "page 4"
  },
  {
    "id": "ariel_gore_527268",
    "url": "https://www.brainyquote.com/quotes/ariel_gore_527268",
    "topic": "Age Quotes",
    "page": "page 4"
  },
  {
    "id": "e_joseph_cossman_176361",
    "url": "https://www.brainyquote.com/quotes/e_joseph_cossman_176361",
    "topic": "Age Quotes",
    "page": "page 4"
  },
  {
    "id": "a_j_foyt_226701",
    "url": "https://www.brainyquote.com/quotes/a_j_foyt_226701",
    "topic": "Age Quotes",
    "page": "page 4"
  },
  {
    "id": "bud_abbott_208475",
    "url": "https://www.brainyquote.com/quotes/bud_abbott_208475",
    "topic": "Age Quotes",
    "page": "page 4"
  },
  {
    "id": "dave_barry_102319",
    "url": "https://www.brainyquote.com/quotes/dave_barry_102319",
    "topic": "Age Quotes",
    "page": "page 4"
  },
  {
    "id": "catherine_bell_298774",
    "url": "https://www.brainyquote.com/quotes/catherine_bell_298774",
    "topic": "Age Quotes",
    "page": "page 4"
  },
  {
    "id": "james_cagney_179645",
    "url": "https://www.brainyquote.com/quotes/james_cagney_179645",
    "topic": "Age Quotes",
    "page": "page 4"
  },
  {
    "id": "marc_andreessen_419426",
    "url": "https://www.brainyquote.com/quotes/marc_andreessen_419426",
    "topic": "Age Quotes",
    "page": "page 4"
  },
  {
    "id": "carroll_shelby_427620",
    "url": "https://www.brainyquote.com/quotes/carroll_shelby_427620",
    "topic": "Age Quotes",
    "page": "page 4"
  },
  {
    "id": "robbie_coltrane_214647",
    "url": "https://www.brainyquote.com/quotes/robbie_coltrane_214647",
    "topic": "Age Quotes",
    "page": "page 4"
  },
  {
    "id": "evel_knievel_326222",
    "url": "https://www.brainyquote.com/quotes/evel_knievel_326222",
    "topic": "Age Quotes",
    "page": "page 4"
  },
  {
    "id": "paul_fussell_402033",
    "url": "https://www.brainyquote.com/quotes/paul_fussell_402033",
    "topic": "Age Quotes",
    "page": "page 4"
  },
  {
    "id": "george_best_253899",
    "url": "https://www.brainyquote.com/quotes/george_best_253899",
    "topic": "Age Quotes",
    "page": "page 5"
  },
  {
    "id": "alexandra_paul_387900",
    "url": "https://www.brainyquote.com/quotes/alexandra_paul_387900",
    "topic": "Age Quotes",
    "page": "page 5"
  },
  {
    "id": "e_b_white_100103",
    "url": "https://www.brainyquote.com/quotes/e_b_white_100103",
    "topic": "Age Quotes",
    "page": "page 5"
  },
  {
    "id": "dale_earnhardt_253600",
    "url": "https://www.brainyquote.com/quotes/dale_earnhardt_253600",
    "topic": "Age Quotes",
    "page": "page 5"
  },
  {
    "id": "james_woolsey_509785",
    "url": "https://www.brainyquote.com/quotes/james_woolsey_509785",
    "topic": "Age Quotes",
    "page": "page 5"
  },
  {
    "id": "e_l_doctorow_154857",
    "url": "https://www.brainyquote.com/quotes/e_l_doctorow_154857",
    "topic": "Age Quotes",
    "page": "page 5"
  },
  {
    "id": "mario_lopez_300197",
    "url": "https://www.brainyquote.com/quotes/mario_lopez_300197",
    "topic": "Age Quotes",
    "page": "page 5"
  },
  {
    "id": "louis_c_k_452732",
    "url": "https://www.brainyquote.com/quotes/louis_c_k_452732",
    "topic": "Age Quotes",
    "page": "page 5"
  },
  {
    "id": "alfred_p_sloan_194030",
    "url": "https://www.brainyquote.com/quotes/alfred_p_sloan_194030",
    "topic": "Age Quotes",
    "page": "page 5"
  },
  {
    "id": "michael_bay_211109",
    "url": "https://www.brainyquote.com/quotes/michael_bay_211109",
    "topic": "Age Quotes",
    "page": "page 5"
  },
  {
    "id": "mitch_hedberg_297438",
    "url": "https://www.brainyquote.com/quotes/mitch_hedberg_297438",
    "topic": "Age Quotes",
    "page": "page 5"
  },
  {
    "id": "scott_baio_419202",
    "url": "https://www.brainyquote.com/quotes/scott_baio_419202",
    "topic": "Age Quotes",
    "page": "page 5"
  },
  {
    "id": "jason_behr_387816",
    "url": "https://www.brainyquote.com/quotes/jason_behr_387816",
    "topic": "Age Quotes",
    "page": "page 5"
  },
  {
    "id": "dudley_moore_195256",
    "url": "https://www.brainyquote.com/quotes/dudley_moore_195256",
    "topic": "Age Quotes",
    "page": "page 5"
  },
  {
    "id": "brock_yates_296273",
    "url": "https://www.brainyquote.com/quotes/brock_yates_296273",
    "topic": "Age Quotes",
    "page": "page 5"
  },
  {
    "id": "elon_musk_567216",
    "url": "https://www.brainyquote.com/quotes/elon_musk_567216",
    "topic": "Age Quotes",
    "page": "page 5"
  },
  {
    "id": "rita_rudner_122725",
    "url": "https://www.brainyquote.com/quotes/rita_rudner_122725",
    "topic": "Age Quotes",
    "page": "page 5"
  },
  {
    "id": "rudolf_diesel_182177",
    "url": "https://www.brainyquote.com/quotes/rudolf_diesel_182177",
    "topic": "Age Quotes",
    "page": "page 5"
  },
  {
    "id": "lara_flynn_boyle_333193",
    "url": "https://www.brainyquote.com/quotes/lara_flynn_boyle_333193",
    "topic": "Age Quotes",
    "page": "page 5"
  },
  {
    "id": "gary_oldman_415708",
    "url": "https://www.brainyquote.com/quotes/gary_oldman_415708",
    "topic": "Age Quotes",
    "page": "page 5"
  },
  {
    "id": "jordana_brewster_432723",
    "url": "https://www.brainyquote.com/quotes/jordana_brewster_432723",
    "topic": "Age Quotes",
    "page": "page 5"
  },
  {
    "id": "lawrence_summers_187383",
    "url": "https://www.brainyquote.com/quotes/lawrence_summers_187383",
    "topic": "Age Quotes",
    "page": "page 5"
  },
  {
    "id": "marshall_mcluhan_102118",
    "url": "https://www.brainyquote.com/quotes/marshall_mcluhan_102118",
    "topic": "Age Quotes",
    "page": "page 5"
  },
  {
    "id": "richard_hammond_498448",
    "url": "https://www.brainyquote.com/quotes/richard_hammond_498448",
    "topic": "Age Quotes",
    "page": "page 5"
  },
  {
    "id": "keanu_reeves_369028",
    "url": "https://www.brainyquote.com/quotes/keanu_reeves_369028",
    "topic": "Age Quotes",
    "page": "page 5"
  },
  {
    "id": "casey_james_523245",
    "url": "https://www.brainyquote.com/quotes/casey_james_523245",
    "topic": "Age Quotes",
    "page": "page 5"
  },
  {
    "id": "mario_andretti_460471",
    "url": "https://www.brainyquote.com/quotes/mario_andretti_460471",
    "topic": "Age Quotes",
    "page": "page 5"
  },
  {
    "id": "al_gore_457740",
    "url": "https://www.brainyquote.com/quotes/al_gore_457740",
    "topic": "Age Quotes",
    "page": "page 5"
  },
  {
    "id": "markpaul_gosselaar_375089",
    "url": "https://www.brainyquote.com/quotes/markpaul_gosselaar_375089",
    "topic": "Age Quotes",
    "page": "page 5"
  },
  {
    "id": "david_attenborough_214826",
    "url": "https://www.brainyquote.com/quotes/david_attenborough_214826",
    "topic": "Age Quotes",
    "page": "page 5"
  },
  {
    "id": "tpain_510714",
    "url": "https://www.brainyquote.com/quotes/tpain_510714",
    "topic": "Age Quotes",
    "page": "page 5"
  },
  {
    "id": "peta_wilson_424449",
    "url": "https://www.brainyquote.com/quotes/peta_wilson_424449",
    "topic": "Age Quotes",
    "page": "page 5"
  },
  {
    "id": "jim_demint_450035",
    "url": "https://www.brainyquote.com/quotes/jim_demint_450035",
    "topic": "Age Quotes",
    "page": "page 5"
  },
  {
    "id": "bill_gates_389269",
    "url": "https://www.brainyquote.com/quotes/bill_gates_389269",
    "topic": "Age Quotes",
    "page": "page 5"
  },
  {
    "id": "lady_gaga_600189",
    "url": "https://www.brainyquote.com/quotes/lady_gaga_600189",
    "topic": "Age Quotes",
    "page": "page 5"
  },
  {
    "id": "jeff_foxworthy_183456",
    "url": "https://www.brainyquote.com/quotes/jeff_foxworthy_183456",
    "topic": "Age Quotes",
    "page": "page 5"
  },
  {
    "id": "elon_musk_567300",
    "url": "https://www.brainyquote.com/quotes/elon_musk_567300",
    "topic": "Age Quotes",
    "page": "page 5"
  },
  {
    "id": "gore_vidal_112493",
    "url": "https://www.brainyquote.com/quotes/gore_vidal_112493",
    "topic": "Age Quotes",
    "page": "page 5"
  },
  {
    "id": "lee_iacocca_456996",
    "url": "https://www.brainyquote.com/quotes/lee_iacocca_456996",
    "topic": "Age Quotes",
    "page": "page 5"
  },
  {
    "id": "tom_arnold_405053",
    "url": "https://www.brainyquote.com/quotes/tom_arnold_405053",
    "topic": "Age Quotes",
    "page": "page 5"
  },
  {
    "id": "ludacris_424222",
    "url": "https://www.brainyquote.com/quotes/ludacris_424222",
    "topic": "Age Quotes",
    "page": "page 5"
  },
  {
    "id": "ryan_tedder_497586",
    "url": "https://www.brainyquote.com/quotes/ryan_tedder_497586",
    "topic": "Age Quotes",
    "page": "page 5"
  },
  {
    "id": "matthew_barney_221011",
    "url": "https://www.brainyquote.com/quotes/matthew_barney_221011",
    "topic": "Age Quotes",
    "page": "page 5"
  },
  {
    "id": "elon_musk_567232",
    "url": "https://www.brainyquote.com/quotes/elon_musk_567232",
    "topic": "Age Quotes",
    "page": "page 5"
  },
  {
    "id": "robert_herjavec_521248",
    "url": "https://www.brainyquote.com/quotes/robert_herjavec_521248",
    "topic": "Age Quotes",
    "page": "page 5"
  },
  {
    "id": "gordon_sinclair_292230",
    "url": "https://www.brainyquote.com/quotes/gordon_sinclair_292230",
    "topic": "Age Quotes",
    "page": "page 5"
  },
  {
    "id": "russell_baker_146118",
    "url": "https://www.brainyquote.com/quotes/russell_baker_146118",
    "topic": "Age Quotes",
    "page": "page 5"
  },
  {
    "id": "sammy_davis_jr_334351",
    "url": "https://www.brainyquote.com/quotes/sammy_davis_jr_334351",
    "topic": "Age Quotes",
    "page": "page 5"
  },
  {
    "id": "ariel_gore_527268",
    "url": "https://www.brainyquote.com/quotes/ariel_gore_527268",
    "topic": "Age Quotes",
    "page": "page 5"
  },
  {
    "id": "e_joseph_cossman_176361",
    "url": "https://www.brainyquote.com/quotes/e_joseph_cossman_176361",
    "topic": "Age Quotes",
    "page": "page 5"
  },
  {
    "id": "a_j_foyt_226701",
    "url": "https://www.brainyquote.com/quotes/a_j_foyt_226701",
    "topic": "Age Quotes",
    "page": "page 5"
  },
  {
    "id": "bud_abbott_208475",
    "url": "https://www.brainyquote.com/quotes/bud_abbott_208475",
    "topic": "Age Quotes",
    "page": "page 5"
  },
  {
    "id": "dave_barry_102319",
    "url": "https://www.brainyquote.com/quotes/dave_barry_102319",
    "topic": "Age Quotes",
    "page": "page 5"
  },
  {
    "id": "catherine_bell_298774",
    "url": "https://www.brainyquote.com/quotes/catherine_bell_298774",
    "topic": "Age Quotes",
    "page": "page 5"
  },
  {
    "id": "james_cagney_179645",
    "url": "https://www.brainyquote.com/quotes/james_cagney_179645",
    "topic": "Age Quotes",
    "page": "page 5"
  },
  {
    "id": "marc_andreessen_419426",
    "url": "https://www.brainyquote.com/quotes/marc_andreessen_419426",
    "topic": "Age Quotes",
    "page": "page 5"
  },
  {
    "id": "carroll_shelby_427620",
    "url": "https://www.brainyquote.com/quotes/carroll_shelby_427620",
    "topic": "Age Quotes",
    "page": "page 5"
  },
  {
    "id": "robbie_coltrane_214647",
    "url": "https://www.brainyquote.com/quotes/robbie_coltrane_214647",
    "topic": "Age Quotes",
    "page": "page 5"
  },
  {
    "id": "evel_knievel_326222",
    "url": "https://www.brainyquote.com/quotes/evel_knievel_326222",
    "topic": "Age Quotes",
    "page": "page 5"
  },
  {
    "id": "paul_fussell_402033",
    "url": "https://www.brainyquote.com/quotes/paul_fussell_402033",
    "topic": "Age Quotes",
    "page": "page 5"
  }
]